resilientftp/__init__.py
resilientftp/resilientftp.py
ResilientFTP-0.1.2.dist-info/LICENSE
ResilientFTP-0.1.2.dist-info/METADATA
ResilientFTP-0.1.2.dist-info/WHEEL
ResilientFTP-0.1.2.dist-info/top_level.txt
ResilientFTP-0.1.2.dist-info/RECORD
