Metadata-Version: 2.2
Name: ResilientFTP
Version: 0.1.2
Summary: Handle FTP connections with automatic retry and reconnection logic.
Home-page: https://github.com/davidlorenzana/ResilientFTP
Author: David Lorenzana Martínez
Author-email: davlorenzana@gmail.com
License: MIT
Classifier: Programming Language :: Python :: 3
Classifier: License :: OSI Approved :: MIT License
Classifier: Operating System :: OS Independent
Requires-Python: >=3.7
License-File: LICENSE
Requires-Dist: tenacity
Dynamic: author
Dynamic: author-email
Dynamic: classifier
Dynamic: description
Dynamic: description-content-type
Dynamic: home-page
Dynamic: license
Dynamic: requires-dist
Dynamic: requires-python
Dynamic: summary
